Metadata-Version: 2.1
Name: crcf
Version: 1.0.0
Summary: Combination Robust Cut Forests
Author-email: "J. Marcus Hughes" <hughes.jmb@gmail.com>
License: MIT License
Classifier: Programming Language :: Python :: 3
Classifier: License :: OSI Approved :: MIT License
Classifier: Operating System :: OS Independent
Requires-Python: >=3.7
Provides-Extra: test
License-File: LICENSE
